colorstamps/__init__.py
colorstamps/helpers.py
colorstamps/stamps.py
colorstamps-0.1.3.dist-info/METADATA
colorstamps-0.1.3.dist-info/WHEEL
colorstamps-0.1.3.dist-info/top_level.txt
colorstamps-0.1.3.dist-info/RECORD
